jembe/__init__.py
jembe/app.py
jembe/common.py
jembe/component.py
jembe/component_config.py
jembe/defaults.py
jembe/exceptions.py
jembe/files.py
jembe/jembe_page.py
jembe/processor.py
jembe/utils.py
jembe/__pycache__/__init__.cpython-38.pyc
jembe/__pycache__/app.cpython-38.pyc
jembe/__pycache__/common.cpython-38.pyc
jembe/__pycache__/component.cpython-38.pyc
jembe/__pycache__/component_config.cpython-38.pyc
jembe/__pycache__/defaults.cpython-38.pyc
jembe/__pycache__/exceptions.cpython-38.pyc
jembe/__pycache__/files.cpython-38.pyc
jembe/__pycache__/jembe_page.cpython-38.pyc
jembe/__pycache__/processor.cpython-38.pyc
jembe/__pycache__/utils.cpython-38.pyc
jembe/cli/__init__.py
jembe/cli/jembe.py
jembe/cli/utils.py
jembe/cli/__pycache__/__init__.cpython-38.pyc
jembe/cli/__pycache__/jembe.cpython-38.pyc
jembe/cli/__pycache__/utils.cpython-38.pyc
jembe/cli/project_templates/basic/.flaskenv.jpt
jembe/cli/project_templates/basic/.gitignore.jpt
jembe/cli/project_templates/basic/LICENSE
jembe/cli/project_templates/basic/README.md
jembe/cli/project_templates/basic/pyproject.toml.jpt
jembe/cli/project_templates/basic/setup.cfg.jpt
jembe/cli/project_templates/basic/setup.py.jpt
jembe/cli/project_templates/basic/instance/config.py.jpt
jembe/cli/project_templates/basic/tests/conftest.py.jpt
jembe/cli/project_templates/basic/{{project_name}}/__init__.py.jpt
jembe/cli/project_templates/basic/{{project_name}}/app.py.jpt
jembe/cli/project_templates/basic/{{project_name}}/commands.py.jpt
jembe/cli/project_templates/basic/{{project_name}}/pages/__init__.py.jpt
jembe/cli/project_templates/basic/{{project_name}}/pages/_counter.py.jpt
jembe/cli/project_templates/basic/{{project_name}}/pages/main.py.jpt
jembe/cli/project_templates/basic/{{project_name}}/static/css/{{project_name}}.css
jembe/cli/project_templates/basic/{{project_name}}/templates/main.html
jembe/cli/project_templates/basic/{{project_name}}/templates/main/counter.html
jembe-0.3.15.dist-info/LICENSE
jembe-0.3.15.dist-info/METADATA
jembe-0.3.15.dist-info/WHEEL
jembe-0.3.15.dist-info/entry_points.txt
jembe-0.3.15.dist-info/top_level.txt
jembe-0.3.15.dist-info/RECORD
