Metadata-Version: 2.1
Name: jembe
Version: 0.3.15
Summary: Jembe Web Framework
Home-page: https://jembe.io
Author: Predrag Peranovic
Author-email: predrag.peranovic@jembe.io
License: LGPL-3.0-or-later
Project-URL: Repository, https://github.com/Jembe/jembe
Keywords: ["framework"]
Classifier: Development Status :: 3 - Alpha
Classifier: Environment :: Web Environment
Classifier: Framework :: Flask
Classifier: Intended Audience :: Developers
Classifier: License :: OSI Approved :: GNU Lesser General Public License v3 or later (LGPLv3+)
Classifier: Programming Language :: Python :: 3.8
Classifier: Topic :: Software Development :: Libraries :: Application Frameworks
Requires-Python: >=3.8
License-File: LICENSE
Requires-Dist: flask (>=1.1.2)
Requires-Dist: lxml (>=4.5.2)
Requires-Dist: simplejson (>=3.17.2)
Provides-Extra: dev
Requires-Dist: black ; extra == 'dev'
Requires-Dist: mypy ; extra == 'dev'
Requires-Dist: pytest ; extra == 'dev'
Requires-Dist: coverage[toml] ; extra == 'dev'
Requires-Dist: watchdog[watchmedo] ; extra == 'dev'
Requires-Dist: sphinx ; extra == 'dev'
Requires-Dist: furo ; extra == 'dev'
